[
    {
        "Model Uploader": "@thanawan-atc",
        "Upload Time": "2023-07-21 12:45:11",
        "Model ID": "sentence-transformers/all-MiniLM-L12-v2",
        "Model Version": "1.0.1",
        "Model Format": "ONNX",
        "Embedding Dimension": "Default",
        "Pooling Mode": "Default"
    },
    {
        "Model Uploader": "@thanawan-atc",
        "Upload Time": "2023-07-21 12:45:11",
        "Model ID": "sentence-transformers/all-MiniLM-L12-v2",
        "Model Version": "1.0.1",
        "Model Format": "TORCH_SCRIPT",
        "Embedding Dimension": "Default",
        "Pooling Mode": "Default"
    },
    {
        "Model Uploader": "@thanawan-atc",
        "Upload Time": "2023-07-21 12:45:38",
        "Model ID": "sentence-transformers/all-MiniLM-L12-v2",
        "Model Version": "1.2.2",
        "Model Format": "ONNX",
        "Embedding Dimension": "Default",
        "Pooling Mode": "Default"
    },
    {
        "Model Uploader": "@thanawan-atc",
        "Upload Time": "2023-07-21 15:23:03",
        "Model ID": "sentence-transformers/msmarco-distilbert-base-tas-b",
        "Model Version": "1.0.1",
        "Model Format": "ONNX",
        "Embedding Dimension": "Default",
        "Pooling Mode": "Default"
    },
    {
        "Model Uploader": "@thanawan-atc",
        "Upload Time": "2023-07-21 15:23:03",
        "Model ID": "sentence-transformers/msmarco-distilbert-base-tas-b",
        "Model Version": "1.0.1",
        "Model Format": "TORCH_SCRIPT",
        "Embedding Dimension": "Default",
        "Pooling Mode": "Default"
    }
]